cp2110/__init__.py
cp2110/easylap.py
pycp2110-1.0.0.dist-info/LICENSE.md
pycp2110-1.0.0.dist-info/METADATA
pycp2110-1.0.0.dist-info/WHEEL
pycp2110-1.0.0.dist-info/top_level.txt
pycp2110-1.0.0.dist-info/zip-safe
pycp2110-1.0.0.dist-info/RECORD
