Metadata-Version: 2.1
Name: pycp2110
Version: 1.0.0
Summary: Silabs CP2110 USB HID to UART bridge library
Home-page: https://github.com/rginda/pycp2110
Author: Robert Ginda
Author-email: rginda@gmail.com
License: MIT
Platform: UNKNOWN
Classifier: Intended Audience :: Developers
Classifier: License :: OSI Approved :: MIT License
Classifier: Operating System :: OS Independent
Classifier: Programming Language :: Python
Classifier: Programming Language :: Python :: 2.6
Classifier: Programming Language :: Python :: 2.7
Classifier: Programming Language :: Python :: 3
Requires-Dist: hid (>=1.0.1)
